alibabacloud_sls20201230/__init__.py
alibabacloud_sls20201230/client.py
alibabacloud_sls20201230/models.py
alibabacloud_sls20201230_py2-5.1.0.dist-info/LICENSE
alibabacloud_sls20201230_py2-5.1.0.dist-info/METADATA
alibabacloud_sls20201230_py2-5.1.0.dist-info/WHEEL
alibabacloud_sls20201230_py2-5.1.0.dist-info/top_level.txt
alibabacloud_sls20201230_py2-5.1.0.dist-info/RECORD
